cesp.py
cesp-1.5.3.dist-info/entry_points.txt
cesp-1.5.3.dist-info/LICENSE.md
cesp-1.5.3.dist-info/WHEEL
cesp-1.5.3.dist-info/METADATA
cesp-1.5.3.dist-info/RECORD
