Metadata-Version: 2.1
Name: cesp
Version: 1.5.3
Summary: Converts blank space to underscore and other characters to avoid problems
License: MIT
Author: Marcus Bruno Fernandes Silva
Author-email: marcusbfs@gmail.com
Requires-Python: >=3.7,<4.0
Classifier: License :: OSI Approved :: MIT License
Classifier: Programming Language :: Python :: 3
Classifier: Programming Language :: Python :: 3.7
Classifier: Programming Language :: Python :: 3.8
Classifier: Programming Language :: Python :: 3.9
Requires-Dist: rich (>=10.2.2,<11.0.0)
